{
    "prefix":  {
                   "codes":  [
                                 "CLMS_WSI"
                             ]
               },
    "product":  {
                    "codes":  [
                                  "FSC"
                              ]
                },
    "pixel_spacing":  {
                          "codes":  [
                                        "020m"
                                    ]
                      },
    "tile_id":  {
                    "format":  "T\u003czone\u003e\u003clat_band\u003e\u003cgrid_square\u003e"
                },
    "sensing_datetime":  {
                             "format":  "YYYYMMDDThhmmss"
                         },
    "platform":  {
                     "codes":  [
                                   "S2A",
                                   "S2B"
                               ]
                 },
    "version":  {
                    "format":  "VXYZ"
                },
    "file_id":  {
                    "codes":  [
                                  "FSCOG",
                                  "FSCOG-QA",
                                  "QAFLAGS",
                                  "CLD",
                                  "NDSI",
                                  "MTD"
                              ]
                },
    "extension":  {
                      "codes":  [
                                    "tif",
                                    "xml"
                                ]
                  },
    "template":  "{prefix}_{product}_{pixel_spacing}_{tile_id}_{sensing_datetime}_{platform}_{version}_{file_id}[.{extension}]",
    "valid_examples":  [
                           "CLMS_WSI_FSC_020m_T32TNS_20211018T103021_S2A_V100_FSCOG.tif"
                       ]
}
